<mujoco model="morphology">
  <option timestep="0.01"/>
  <default>
    <default class="/"/>
    <default class="0/"/>
    <default class="0/1/"/>
    <default class="0/1/2/"/>
    <default class="0/1/2/3/"/>
    <default class="0/1/2/4/"/>
    <default class="0/1/2/4/5/"/>
    <default class="0/1/2/4/6/"/>
    <default class="0/1/2/4/6/7/"/>
    <default class="0/1/2/4/6/7/8/"/>
    <default class="0/1/2/4/6/7/9/"/>
    <default class="0/1/10/"/>
  </default>
  <asset>
    <texture name="texplane" type="2d" builtin="checker" rgb1="0.10000000000000001 0.20000000000000001 0.29999999999999999" rgb2="0.20000000000000001 0.29999999999999999 0.40000000000000002" width="300" height="300"/>
    <material name="MatPlane" class="/" texture="texplane" texrepeat="20 20" specular="1" shininess="1" reflectance="0.5"/>
  </asset>
  <worldbody>
    <light name="//unnamed_light_0" class="/" directional="true" pos="0 0 1.5" dir="0 0 -1.3" cutoff="100" exponent="1" diffuse="1 1 1" specular="0.10000000000000001 0.10000000000000001 0.10000000000000001"/>
    <geom name="ground" class="/" type="plane" size="15 15 0.5" material="MatPlane" rgba="1 1 1 1"/>
    <site name="body" class="/" size="9.9999999999999995e-07 9.9999999999999995e-07 9.9999999999999995e-07" pos="0 0 1.5300401210784913"/>
    <body pos="0 0 1.5300401210784913" name="0/">
      <joint name="0/rootx/" class="/" type="slide" axis="1 0 0" limited="false" stiffness="0" armature="0" damping="0"/>
      <joint name="0/rootz/" class="/" type="slide" axis="0 0 1" limited="false" stiffness="0" armature="0" damping="0"/>
      <joint name="0/rooty/" class="/" type="hinge" axis="0 1 0" limited="false" stiffness="0" armature="0" damping="0"/>
      <geom name="0/geom" class="0/" type="capsule" contype="1" conaffinity="1" condim="3" size="0.057316337935166911" rgba="0.16601490198592128 0.58552024719703633 0.82671762298615925 1" friction="0.59999999999999998 0.10000000000000001 0.10000000000000001" fromto="0 0 0 -0.71993491554773659 0 -0.38075990136930665"/>
      <site name="0/end0" class="0/" size="0.0050000000000000001" pos="-0.71993491554773659 0 -0.38075990136930665"/>
      <site name="0/attach1" class="0/" size="9.9999999999999995e-07 9.9999999999999995e-07 9.9999999999999995e-07" pos="-0.45030785260041811 0 -0.23815926945494917"/>
      <body pos="-0.45030785260041811 0 -0.23815926945494917" name="0/1/">
        <joint name="0/1/joint/" class="0/" type="hinge" axis="0 1 0" limited="true" range="-53.354050288664567 53.354050288664567"/>
        <geom name="0/1/geom" class="0/1/" type="capsule" contype="1" conaffinity="1" condim="3" size="0.063629963072306339" rgba="0.63803736303354819 0.96229547335382071 0.27660666599015082 1" friction="0.59999999999999998 0.10000000000000001 0.10000000000000001" fromto="0 0 0 0.56477568606398076 0 -0.73017851075767837"/>
        <site name="0/1/end1" class="0/1/" size="0.0050000000000000001" pos="0.56477568606398076 0 -0.73017851075767837"/>
        <site name="0/1/attach2" class="0/1/" size="9.9999999999999995e-07 9.9999999999999995e-07 9.9999999999999995e-07" pos="0.26212219677319959 0 -0.33888851804201725"/>
        <body pos="0.26212219677319959 0 -0.33888851804201725" name="0/1/2/">
          <joint name="0/1/2/joint/" class="0/1/" type="hinge" axis="0 1 0" limited="true" range="-38.687447717589563 38.687447717589563"/>
          <geom name="0/1/2/geom" class="0/1/2/" type="capsule" contype="1" conaffinity="1" condim="3" size="0.052352955070050396" rgba="0.13450209288001902 0.015285924261667638 0.3579893641230486 1" friction="0.59999999999999998 0.10000000000000001 0.10000000000000001" fromto="0 0 0 0.73471594485408209 0 -0.071019676161072853"/>
          <site name="0/1/2/end2" class="0/1/2/" size="0.0050000000000000001" pos="0.73471594485408209 0 -0.071019676161072853"/>
          <site name="0/1/2/attach3" class="0/1/2/" size="9.9999999999999995e-07 9.9999999999999995e-07 9.9999999999999995e-07" pos="0.20009596071769198 0 -0.01934182922099446"/>
          <body pos="0.20009596071769198 0 -0.01934182922099446" name="0/1/2/3/">
            <geom name="0/1/2/3/geom" class="0/1/2/3/" type="capsule" contype="1" conaffinity="1" condim="3" size="0.06009136674693924" rgba="0.6255627824210106 0.18156598878047314 0.76179084760283589 1" friction="0.59999999999999998 0.10000000000000001 0.10000000000000001" fromto="0 0 0 0.49888099913349326 0 0.68441954268034655"/>
            <site name="0/1/2/3/end3" class="0/1/2/3/" size="0.0050000000000000001" pos="0.49888099913349326 0 0.68441954268034655"/>
          </body>
          <site name="0/1/2/attach4" class="0/1/2/" size="9.9999999999999995e-07 9.9999999999999995e-07 9.9999999999999995e-07" pos="0.38409748813114625 0 -0.037127925986107681"/>
          <body pos="0.38409748813114625 0 -0.037127925986107681" name="0/1/2/4/">
            <joint name="0/1/2/4/joint/" class="0/1/2/" type="hinge" axis="0 1 0" limited="true" range="-41.993866944089412 41.993866944089412"/>
            <geom name="0/1/2/4/geom" class="0/1/2/4/" type="capsule" contype="1" conaffinity="1" condim="3" size="0.054234689003071039" rgba="0.48698130971069542 0.13096967634288537 0.19568803162339932 1" friction="0.59999999999999998 0.10000000000000001 0.10000000000000001" fromto="0 0 0 0.0054414029631206784 0 -0.70143114697099818"/>
            <site name="0/1/2/4/end4" class="0/1/2/4/" size="0.0050000000000000001" pos="0.0054414029631206784 0 -0.70143114697099818"/>
            <site name="0/1/2/4/attach5" class="0/1/2/4/" size="9.9999999999999995e-07 9.9999999999999995e-07 9.9999999999999995e-07" pos="0.0049585490252664248 0 -0.63918823025557592"/>
            <body pos="0.0049585490252664248 0 -0.63918823025557592" name="0/1/2/4/5/">
              <joint name="0/1/2/4/5/joint/" class="0/1/2/4/" type="hinge" axis="0 1 0" limited="true" range="-48.205673054651399 48.205673054651399"/>
              <geom name="0/1/2/4/5/geom" class="0/1/2/4/5/" type="capsule" contype="1" conaffinity="1" condim="3" size="0.050323449743968934" rgba="0.10311630254525872 0.46037205433955841 0.51674564846563864 1" friction="0.59999999999999998 0.10000000000000001 0.10000000000000001" fromto="0 0 0 0.39200414246395709 0 0.034320207395018176"/>
              <site name="0/1/2/4/5/end5" class="0/1/2/4/5/" size="0.0050000000000000001" pos="0.39200414246395709 0 0.034320207395018176"/>
            </body>
            <site name="0/1/2/4/attach6" class="0/1/2/4/" size="9.9999999999999995e-07 9.9999999999999995e-07 9.9999999999999995e-07" pos="0.0031508715310701843 0 -0.40616720485065994"/>
            <body pos="0.0031508715310701843 0 -0.40616720485065994" name="0/1/2/4/6/">
              <joint name="0/1/2/4/6/joint/" class="0/1/2/4/" type="hinge" axis="0 1 0" limited="true" range="-66.855822067507674 66.855822067507674"/>
              <geom name="0/1/2/4/6/geom" class="0/1/2/4/6/" type="capsule" contype="1" conaffinity="1" condim="3" size="0.043991252906667708" rgba="0.16954998473962801 0.22797745471434328 0.22582746600540304 1" friction="0.59999999999999998 0.10000000000000001 0.10000000000000001" fromto="0 0 0 0.59631726809218 0 0.050726265491499167"/>
              <site name="0/1/2/4/6/end6" class="0/1/2/4/6/" size="0.0050000000000000001" pos="0.59631726809218 0 0.050726265491499167"/>
              <site name="0/1/2/4/6/attach7" class="0/1/2/4/6/" size="9.9999999999999995e-07 9.9999999999999995e-07 9.9999999999999995e-07" pos="0.28728665743089399 0 0.024438298262984694"/>
              <body pos="0.28728665743089399 0 0.024438298262984694" name="0/1/2/4/6/7/">
                <joint name="0/1/2/4/6/7/joint/" class="0/1/2/4/6/" type="hinge" axis="0 1 0" limited="true" range="-43.457042157904489 43.457042157904489"/>
                <geom name="0/1/2/4/6/7/geom" class="0/1/2/4/6/7/" type="capsule" contype="1" conaffinity="1" condim="3" size="0.048201922352985108" rgba="0.93085529250607535 0.46289732876939738 0.40552083509899572 1" friction="0.59999999999999998 0.10000000000000001 0.10000000000000001" fromto="0 0 0 0.33981723736013247 0 -0.34369979763189668"/>
                <site name="0/1/2/4/6/7/end7" class="0/1/2/4/6/7/" size="0.0050000000000000001" pos="0.33981723736013247 0 -0.34369979763189668"/>
                <site name="0/1/2/4/6/7/attach8" class="0/1/2/4/6/7/" size="9.9999999999999995e-07 9.9999999999999995e-07 9.9999999999999995e-07" pos="0.33826133518584023 0 -0.34212611859609032"/>
                <body pos="0.33826133518584023 0 -0.34212611859609032" name="0/1/2/4/6/7/8/">
                  <joint name="0/1/2/4/6/7/8/joint/" class="0/1/2/4/6/7/" type="hinge" axis="0 1 0" limited="true" range="-67.869402725375622 67.869402725375622"/>
                  <geom name="0/1/2/4/6/7/8/geom" class="0/1/2/4/6/7/8/" type="capsule" contype="1" conaffinity="1" condim="3" size="0.052015534049431489" rgba="0.65810719585288147 0.19637608348157953 0.48715971865796637 1" friction="0.59999999999999998 0.10000000000000001 0.10000000000000001" fromto="0 0 0 0.49785519892642105 0 0.088128880372468799"/>
                  <site name="0/1/2/4/6/7/8/end8" class="0/1/2/4/6/7/8/" size="0.0050000000000000001" pos="0.49785519892642105 0 0.088128880372468799"/>
                </body>
                <site name="0/1/2/4/6/7/attach9" class="0/1/2/4/6/7/" size="9.9999999999999995e-07 9.9999999999999995e-07 9.9999999999999995e-07" pos="0.30489652878866846 0 -0.30838010472163135"/>
                <body pos="0.30489652878866846 0 -0.30838010472163135" name="0/1/2/4/6/7/9/">
                  <geom name="0/1/2/4/6/7/9/geom" class="0/1/2/4/6/7/9/" type="capsule" contype="1" conaffinity="1" condim="3" size="0.068577681548171912" rgba="0.32907375852232057 0.23524678513526243 0.75252455978368848 1" friction="0.59999999999999998 0.10000000000000001 0.10000000000000001" fromto="0 0 0 0.050670680549597558 0 0.20978632870883207"/>
                  <site name="0/1/2/4/6/7/9/end9" class="0/1/2/4/6/7/9/" size="0.0050000000000000001" pos="0.050670680549597558 0 0.20978632870883207"/>
                </body>
              </body>
            </body>
          </body>
        </body>
        <site name="0/1/attach10" class="0/1/" size="9.9999999999999995e-07 9.9999999999999995e-07 9.9999999999999995e-07" pos="0.37521330464350283 0 -0.48510001184793022"/>
        <body pos="0.37521330464350283 0 -0.48510001184793022" name="0/1/10/">
          <geom name="0/1/10/geom" class="0/1/10/" type="capsule" contype="1" conaffinity="1" condim="3" size="0.055577154028898214" rgba="0.20381079279694159 0.45434426052772936 0.19373275795291656 1" friction="0.59999999999999998 0.10000000000000001 0.10000000000000001" fromto="0 0 0 -0.1768167404522456 0 -0.70678087526949918"/>
          <site name="0/1/10/end10" class="0/1/10/" size="0.0050000000000000001" pos="-0.1768167404522456 0 -0.70678087526949918"/>
        </body>
      </body>
      <camera name="0/side" class="0/" mode="trackcom" pos="0.40000000000000002 -4 0.20000000000000001" quat="0.70699999999999996 0.70699999999999996 0 0"/>
    </body>
  </worldbody>
  <actuator>
    <motor name="0/1/motor" class="0/1/" ctrllimited="true" ctrlrange="-1 1" gear="74" joint="0/1/joint/"/>
    <motor name="0/1/2/motor" class="0/1/2/" ctrllimited="true" ctrlrange="-1 1" gear="65" joint="0/1/2/joint/"/>
    <motor name="0/1/2/4/motor" class="0/1/2/4/" ctrllimited="true" ctrlrange="-1 1" gear="59" joint="0/1/2/4/joint/"/>
    <motor name="0/1/2/4/5/motor" class="0/1/2/4/5/" ctrllimited="true" ctrlrange="-1 1" gear="55" joint="0/1/2/4/5/joint/"/>
    <motor name="0/1/2/4/6/motor" class="0/1/2/4/6/" ctrllimited="true" ctrlrange="-1 1" gear="53" joint="0/1/2/4/6/joint/"/>
    <motor name="0/1/2/4/6/7/motor" class="0/1/2/4/6/7/" ctrllimited="true" ctrlrange="-1 1" gear="79" joint="0/1/2/4/6/7/joint/"/>
    <motor name="0/1/2/4/6/7/8/motor" class="0/1/2/4/6/7/8/" ctrllimited="true" ctrlrange="-1 1" gear="56" joint="0/1/2/4/6/7/8/joint/"/>
  </actuator>
  <sensor>
    <subtreelinvel name="velocity" body="0/"/>
  </sensor>
</mujoco>
