<mujoco model="morphology">
  <option timestep="0.01"/>
  <default>
    <default class="/"/>
    <default class="0/"/>
    <default class="0/1/"/>
    <default class="0/1/2/"/>
    <default class="0/1/3/"/>
    <default class="0/1/3/4/"/>
    <default class="0/1/3/4/5/"/>
    <default class="0/1/3/4/5/6/"/>
    <default class="0/1/3/4/7/"/>
    <default class="0/8/"/>
    <default class="0/9/"/>
    <default class="0/9/10/"/>
  </default>
  <asset>
    <texture name="texplane" type="2d" builtin="checker" rgb1="0.10000000000000001 0.20000000000000001 0.29999999999999999" rgb2="0.20000000000000001 0.29999999999999999 0.40000000000000002" width="300" height="300"/>
    <material name="MatPlane" class="/" texture="texplane" texrepeat="20 20" specular="1" shininess="1" reflectance="0.5"/>
  </asset>
  <worldbody>
    <light name="//unnamed_light_0" class="/" directional="true" pos="0 0 1.5" dir="0 0 -1.3" cutoff="100" exponent="1" diffuse="1 1 1" specular="0.10000000000000001 0.10000000000000001 0.10000000000000001"/>
    <geom name="ground" class="/" type="plane" size="15 15 0.5" material="MatPlane" rgba="1 1 1 1"/>
    <site name="body" class="/" size="9.9999999999999995e-07 9.9999999999999995e-07 9.9999999999999995e-07" pos="0 0 0.47005272507667539"/>
    <body pos="0 0 0.47005272507667539" name="0/">
      <joint name="0/rootx/" class="/" type="slide" axis="1 0 0" limited="false" stiffness="0" armature="0" damping="0"/>
      <joint name="0/rootz/" class="/" type="slide" axis="0 0 1" limited="false" stiffness="0" armature="0" damping="0"/>
      <joint name="0/rooty/" class="/" type="hinge" axis="0 1 0" limited="false" stiffness="0" armature="0" damping="0"/>
      <geom name="0/geom" class="0/" type="capsule" contype="1" conaffinity="1" condim="3" size="0.045420561973364595" rgba="0.93685405745889072 0.48484791813836337 0.92966519765190281 1" friction="0.59999999999999998 0.10000000000000001 0.10000000000000001" fromto="0 0 0 -0.37080606239515401 0 0.12481289410402385"/>
      <site name="0/end0" class="0/" size="0.0050000000000000001" pos="-0.37080606239515401 0 0.12481289410402385"/>
      <site name="0/attach1" class="0/" size="9.9999999999999995e-07 9.9999999999999995e-07 9.9999999999999995e-07" pos="-0.24117266152631348 0 0.081178440474879196"/>
      <body pos="-0.24117266152631348 0 0.081178440474879196" name="0/1/">
        <joint name="0/1/joint/" class="0/" type="hinge" axis="0 1 0" limited="true" stiffness="100" range="-66.032414710184952 66.032414710184952" armature="0.20000000000000001" damping="3.5"/>
        <geom name="0/1/geom" class="0/1/" type="capsule" contype="1" conaffinity="1" condim="3" size="0.050262718760220731" rgba="0.87028066092281764 0.047915182859588734 0.67432900040280286 1" friction="0.59999999999999998 0.10000000000000001 0.10000000000000001" fromto="0 0 0 0.18086329073681662 0 0.17932993457515789"/>
        <site name="0/1/end1" class="0/1/" size="0.0050000000000000001" pos="0.18086329073681662 0 0.17932993457515789"/>
        <site name="0/1/attach2" class="0/1/" size="9.9999999999999995e-07 9.9999999999999995e-07 9.9999999999999995e-07" pos="0.16823988534608975 0 0.16681355021870578"/>
        <body pos="0.16823988534608975 0 0.16681355021870578" name="0/1/2/">
          <joint name="0/1/2/joint/" class="0/1/" type="hinge" axis="0 1 0" limited="true" stiffness="100" range="-38.934717041872787 38.934717041872787" armature="0.20000000000000001" damping="3.5"/>
          <geom name="0/1/2/geom" class="0/1/2/" type="capsule" contype="1" conaffinity="1" condim="3" size="0.044806452306163272" rgba="0.56388149464079962 0.598955989840533 0.63418575124886112 1" friction="0.59999999999999998 0.10000000000000001 0.10000000000000001" fromto="0 0 0 -0.73164373246463521 0 0.57993447137026277"/>
          <site name="0/1/2/end2" class="0/1/2/" size="0.0050000000000000001" pos="-0.73164373246463521 0 0.57993447137026277"/>
        </body>
        <site name="0/1/attach3" class="0/1/" size="9.9999999999999995e-07 9.9999999999999995e-07 9.9999999999999995e-07" pos="0.10255056600233162 0 0.10168114390113761"/>
        <body pos="0.10255056600233162 0 0.10168114390113761" name="0/1/3/">
          <joint name="0/1/3/joint/" class="0/1/" type="hinge" axis="0 1 0" limited="true" stiffness="100" range="-39.522939575015542 39.522939575015542" armature="0.20000000000000001" damping="3.5"/>
          <geom name="0/1/3/geom" class="0/1/3/" type="capsule" contype="1" conaffinity="1" condim="3" size="0.064773883073355187" rgba="0.030675428017918338 0.36512046467285819 0.60063726450000343 1" friction="0.59999999999999998 0.10000000000000001 0.10000000000000001" fromto="0 0 0 0.45437124455152311 0 -0.23716631243098651"/>
          <site name="0/1/3/end3" class="0/1/3/" size="0.0050000000000000001" pos="0.45437124455152311 0 -0.23716631243098651"/>
          <site name="0/1/3/attach4" class="0/1/3/" size="9.9999999999999995e-07 9.9999999999999995e-07 9.9999999999999995e-07" pos="0.4450179937375926 0 -0.23228423410542803"/>
          <body pos="0.4450179937375926 0 -0.23228423410542803" name="0/1/3/4/">
            <joint name="0/1/3/4/joint/" class="0/1/3/" type="hinge" axis="0 1 0" limited="true" stiffness="100" range="-65.840356734945686 65.840356734945686" armature="0.20000000000000001" damping="3.5"/>
            <geom name="0/1/3/4/geom" class="0/1/3/4/" type="capsule" contype="1" conaffinity="1" condim="3" size="0.04562873023894163" rgba="0.91364126805486301 0.91420504681832793 0.89145931699198688 1" friction="0.59999999999999998 0.10000000000000001 0.10000000000000001" fromto="0 0 0 0.52041474906098428 0 0.17934362330706488"/>
            <site name="0/1/3/4/end4" class="0/1/3/4/" size="0.0050000000000000001" pos="0.52041474906098428 0 0.17934362330706488"/>
            <site name="0/1/3/4/attach5" class="0/1/3/4/" size="9.9999999999999995e-07 9.9999999999999995e-07 9.9999999999999995e-07" pos="0.14689378635517422 0 0.050622054685740055"/>
            <body pos="0.14689378635517422 0 0.050622054685740055" name="0/1/3/4/5/">
              <geom name="0/1/3/4/5/geom" class="0/1/3/4/5/" type="capsule" contype="1" conaffinity="1" condim="3" size="0.057298142979209987" rgba="0.99685574239053565 0.97387453127257972 0.44147185725094074 1" friction="0.59999999999999998 0.10000000000000001 0.10000000000000001" fromto="0 0 0 -0.35655778855271514 0 0.69613887503382288"/>
              <site name="0/1/3/4/5/end5" class="0/1/3/4/5/" size="0.0050000000000000001" pos="-0.35655778855271514 0 0.69613887503382288"/>
              <site name="0/1/3/4/5/attach6" class="0/1/3/4/5/" size="9.9999999999999995e-07 9.9999999999999995e-07 9.9999999999999995e-07" pos="-0.2113504461532425 0 0.41263791325445276"/>
              <body pos="-0.2113504461532425 0 0.41263791325445276" name="0/1/3/4/5/6/">
                <geom name="0/1/3/4/5/6/geom" class="0/1/3/4/5/6/" type="capsule" contype="1" conaffinity="1" condim="3" size="0.053172118719223241" rgba="0.54516057498110837 0.27076729809357392 0.36918391989780641 1" friction="0.59999999999999998 0.10000000000000001 0.10000000000000001" fromto="0 0 0 0.59821316283681014 0 0.70881618829273396"/>
                <site name="0/1/3/4/5/6/end6" class="0/1/3/4/5/6/" size="0.0050000000000000001" pos="0.59821316283681014 0 0.70881618829273396"/>
              </body>
            </body>
            <site name="0/1/3/4/attach7" class="0/1/3/4/" size="9.9999999999999995e-07 9.9999999999999995e-07 9.9999999999999995e-07" pos="0.23840813546332018 0 0.082159429410911949"/>
            <body pos="0.23840813546332018 0 0.082159429410911949" name="0/1/3/4/7/">
              <geom name="0/1/3/4/7/geom" class="0/1/3/4/7/" type="capsule" contype="1" conaffinity="1" condim="3" size="0.069133335855391206" rgba="0.42206278502600381 0.52925929712329267 0.25362606362005524 1" friction="0.59999999999999998 0.10000000000000001 0.10000000000000001" fromto="0 0 0 -0.05393454589817126 0 0.46544960070507591"/>
              <site name="0/1/3/4/7/end7" class="0/1/3/4/7/" size="0.0050000000000000001" pos="-0.05393454589817126 0 0.46544960070507591"/>
            </body>
          </body>
        </body>
      </body>
      <site name="0/attach8" class="0/" size="9.9999999999999995e-07 9.9999999999999995e-07 9.9999999999999995e-07" pos="-0.23687046814374202 0 0.079730327130654269"/>
      <body pos="-0.23687046814374202 0 0.079730327130654269" name="0/8/">
        <joint name="0/8/joint/" class="0/" type="hinge" axis="0 1 0" limited="true" stiffness="100" range="-69.823623465251927 69.823623465251927" armature="0.20000000000000001" damping="3.5"/>
        <geom name="0/8/geom" class="0/8/" type="capsule" contype="1" conaffinity="1" condim="3" size="0.053259887346456376" rgba="0.22180572800104015 0.39340449820502787 0.62962125702186422 1" friction="0.59999999999999998 0.10000000000000001 0.10000000000000001" fromto="0 0 0 -0.69970026959111764 0 -0.40622224466722145"/>
        <site name="0/8/end8" class="0/8/" size="0.0050000000000000001" pos="-0.69970026959111764 0 -0.40622224466722145"/>
      </body>
      <site name="0/attach9" class="0/" size="9.9999999999999995e-07 9.9999999999999995e-07 9.9999999999999995e-07" pos="-0.18157835668374098 0 0.061119066009764932"/>
      <body pos="-0.18157835668374098 0 0.061119066009764932" name="0/9/">
        <geom name="0/9/geom" class="0/9/" type="capsule" contype="1" conaffinity="1" condim="3" size="0.060766249458593311" rgba="0.038971886114961496 0.85340584590434299 0.32325695790118469 1" friction="0.59999999999999998 0.10000000000000001 0.10000000000000001" fromto="0 0 0 -0.058258447877550523 0 -0.43117179888461321"/>
        <site name="0/9/end9" class="0/9/" size="0.0050000000000000001" pos="-0.058258447877550523 0 -0.43117179888461321"/>
        <site name="0/9/attach10" class="0/9/" size="9.9999999999999995e-07 9.9999999999999995e-07 9.9999999999999995e-07" pos="-0.042185924756908258 0 -0.31221877217323224"/>
        <body pos="-0.042185924756908258 0 -0.31221877217323224" name="0/9/10/">
          <joint name="0/9/10/joint/" class="0/9/" type="hinge" axis="0 1 0" limited="true" stiffness="100" range="-51.286139112891227 51.286139112891227" armature="0.20000000000000001" damping="3.5"/>
          <geom name="0/9/10/geom" class="0/9/10/" type="capsule" contype="1" conaffinity="1" condim="3" size="0.044681741791357782" rgba="0.048105854431675255 0.091080843711668136 0.55473392201421112 1" friction="0.59999999999999998 0.10000000000000001 0.10000000000000001" fromto="0 0 0 0.7023482522149298 0 -0.05578280262663271"/>
          <site name="0/9/10/end10" class="0/9/10/" size="0.0050000000000000001" pos="0.7023482522149298 0 -0.05578280262663271"/>
        </body>
      </body>
      <camera name="0/side" class="0/" mode="trackcom" pos="0.40000000000000002 -4 0.20000000000000001" quat="0.70699999999999996 0.70699999999999996 0 0"/>
    </body>
  </worldbody>
  <actuator>
    <motor name="0/1/motor" class="0/1/" ctrllimited="true" ctrlrange="-1 1" gear="82" joint="0/1/joint/"/>
    <motor name="0/1/2/motor" class="0/1/2/" ctrllimited="true" ctrlrange="-1 1" gear="84" joint="0/1/2/joint/"/>
    <motor name="0/1/3/motor" class="0/1/3/" ctrllimited="true" ctrlrange="-1 1" gear="69" joint="0/1/3/joint/"/>
    <motor name="0/1/3/4/motor" class="0/1/3/4/" ctrllimited="true" ctrlrange="-1 1" gear="82" joint="0/1/3/4/joint/"/>
    <motor name="0/8/motor" class="0/8/" ctrllimited="true" ctrlrange="-1 1" gear="84" joint="0/8/joint/"/>
    <motor name="0/9/10/motor" class="0/9/10/" ctrllimited="true" ctrlrange="-1 1" gear="56" joint="0/9/10/joint/"/>
  </actuator>
  <sensor>
    <subtreelinvel name="velocity" body="0/"/>
  </sensor>
</mujoco>
